geometric_primitives/__init__.py
geometric_primitives/brick.py
geometric_primitives/bricks.py
geometric_primitives/utils_brick.py
geometric_primitives/utils_bricks.py
geometric_primitives/utils_io.py
geometric_primitives/utils_meshes.py
geometric_primitives/utils_validation.py
geometric_primitives/voxels.py
geometric_primitives/rules/__init__.py
geometric_primitives/rules/rules_1_2.py
geometric_primitives/rules/rules_2_2.py
geometric_primitives/rules/rules_2_4.py
geometric_primitives/rules/rules_mixed_12_22.py
geometric_primitives/rules/rules_mixed_12_24.py
geometric_primitives/rules/rules_mixed_22_12.py
geometric_primitives/rules/rules_mixed_22_24.py
geometric_primitives/rules/rules_mixed_24_12.py
geometric_primitives/rules/rules_mixed_24_22.py
geometric_primitives-0.1.2.dist-info/LICENSE
geometric_primitives-0.1.2.dist-info/METADATA
geometric_primitives-0.1.2.dist-info/WHEEL
geometric_primitives-0.1.2.dist-info/top_level.txt
geometric_primitives-0.1.2.dist-info/RECORD
