Metadata-Version: 2.1
Name: geometric-primitives
Version: 0.1.2
Summary: This package helps to construct a 3D shape.
Home-page: https://github.com/POSTECH-CVLab/Geometric-Primitives
Author: Jungtaek Kim
Author-email: jtkim@postech.ac.kr
License: MIT
Classifier: Programming Language :: Python :: 3.6
Classifier: Programming Language :: Python :: 3.7
Classifier: Programming Language :: Python :: 3.8
Classifier: Programming Language :: Python :: 3.9
Classifier: License :: OSI Approved :: MIT License
Classifier: Topic :: Scientific/Engineering
Classifier: Topic :: Scientific/Engineering :: Artificial Intelligence
Requires-Python: >=3.6, <4
License-File: LICENSE
Requires-Dist: numpy
Requires-Dist: open3d
